coally_sql/__init__.py
coally_sql/_assets.py
coally_sql/csv_utils.py
coally_sql/py.typed
coally_sql/ui.py
coally_sql-0.1.6.dist-info/METADATA
coally_sql-0.1.6.dist-info/WHEEL
coally_sql-0.1.6.dist-info/RECORD
